README.rst
setup.py
Mage2Gen.egg-info/PKG-INFO
Mage2Gen.egg-info/SOURCES.txt
Mage2Gen.egg-info/dependency_links.txt
Mage2Gen.egg-info/top_level.txt
bin/mage2gen
mage2gen/__init__.py
mage2gen/license.py
mage2gen/module.py
mage2gen/snippet.py
mage2gen/utils.py
mage2gen/licenses/apache2.txt
mage2gen/licenses/apache2_short.txt
mage2gen/licenses/gplv3.txt
mage2gen/licenses/gplv3_short.txt
mage2gen/licenses/mit.txt
mage2gen/licenses/mit_short.txt
mage2gen/licenses/oslv3.txt
mage2gen/licenses/oslv3_short.txt
mage2gen/snippets/__init__.py
mage2gen/snippets/api.py
mage2gen/snippets/block.py
mage2gen/snippets/cache.py
mage2gen/snippets/categoryattribute.py
mage2gen/snippets/companyattribute.py
mage2gen/snippets/component.py
mage2gen/snippets/configurationtype.py
mage2gen/snippets/console.py
mage2gen/snippets/controller.py
mage2gen/snippets/cronjob.py
mage2gen/snippets/customerattribute.py
mage2gen/snippets/eaventity.py
mage2gen/snippets/eaventityattribute.py
mage2gen/snippets/graphql.py
mage2gen/snippets/helper.py
mage2gen/snippets/install.py
mage2gen/snippets/language.py
mage2gen/snippets/model.py
mage2gen/snippets/observer.py
mage2gen/snippets/payment.py
mage2gen/snippets/plugin.py
mage2gen/snippets/preference.py
mage2gen/snippets/productattribute.py
mage2gen/snippets/producttype.py
mage2gen/snippets/saleattribute.py
mage2gen/snippets/shipping.py
mage2gen/snippets/system.py
mage2gen/snippets/uicomponent.py
mage2gen/snippets/unittest.py
mage2gen/snippets/viewmodel.py
mage2gen/snippets/widget.py
mage2gen/templates/class.tmpl
mage2gen/templates/email.tmpl
mage2gen/templates/graphqlobject.tmpl
mage2gen/templates/graphqlobjectitem.tmpl
mage2gen/templates/graphqlschema.tmpl
mage2gen/templates/interface.tmpl
mage2gen/templates/interfacemethod.tmpl
mage2gen/templates/method.tmpl
mage2gen/templates/producttype.tmpl
mage2gen/templates/registration.tmpl
mage2gen/templates/shipping.tmpl
mage2gen/templates/staticfile.tmpl
mage2gen/templates/attributes/categoryattribute.tmpl
mage2gen/templates/attributes/companyattribute.tmpl
mage2gen/templates/attributes/customeraddressattribute.tmpl
