Metadata-Version: 1.1
Name: Mage2Gen
Version: 2.3.3
Summary: Magento 2 module generator
Home-page: https://github.com/krukas/Mage2Gen
Author: Maikel Martens
Author-email: maikel@martens.me
License: GPL3
Download-URL: https://github.com/krukas/Mage2Gen/releases/tag/2.3.3
Keywords: Magento,Magento2,module,generator,mage2gen
Platform: UNKNOWN
Classifier: License :: OSI Approved :: GNU General Public License v3 (GPLv3)
Classifier: Programming Language :: Python :: 3
Classifier: Topic :: Software Development :: Code Generators
